den/__init__.py
den/clustering.py
den/functions.py
testy123890-0.0.1.4.dist-info/LICENSE
testy123890-0.0.1.4.dist-info/METADATA
testy123890-0.0.1.4.dist-info/WHEEL
testy123890-0.0.1.4.dist-info/top_level.txt
testy123890-0.0.1.4.dist-info/RECORD
