Metadata-Version: 2.1
Name: testy123890
Version: 0.0.1.4
Summary: This is the package for DenMune Clustering Algorithm published in paper https://doi.org/10.1016/j.patcog.2020.107589
Home-page: https://github.com/pypa/sampleproject
Author: Mohamed Ali Abbas
Author-email: mohamed.alyabbas@outlook.com
License: UNKNOWN
Project-URL: Bug Tracker, https://github.com/pypa/sampleproject/issues
Platform: UNKNOWN
Classifier: Programming Language :: Python :: 3
Classifier: License :: OSI Approved :: MIT License
Classifier: Operating System :: OS Independent
Requires-Python: >=3.6
License-File: LICENSE
Requires-Dist: numpy (>=1.18.5)
Requires-Dist: pandas (>=1.0.3)
Requires-Dist: matplotlib (>=3.2.1)
Requires-Dist: scikit-learn (>=0.22.1)
Requires-Dist: seaborn (>=0.10.1)
Requires-Dist: ngt (>=1.11.6)
Requires-Dist: anytree (>=2.8.0)
Requires-Dist: pybind11
